happy_scientists-0.1.0.dist-info/DESCRIPTION.rst
happy_scientists-0.1.0.dist-info/METADATA
happy_scientists-0.1.0.dist-info/RECORD
happy_scientists-0.1.0.dist-info/WHEEL
happy_scientists-0.1.0.dist-info/metadata.json
happy_scientists-0.1.0.dist-info/top_level.txt
happyscientists/__init__.py
happyscientists/scientistsgenerator.py
happyscientists/scientistsgenerator_test.py
