Metadata-Version: 2.0
Name: happy-scientists
Version: 0.1.0
Summary: Library for generate funny random scientists names
Home-page: https://github.com/Bignone/happy-scientists
Author: Eduardo Bustos
Author-email: eduardobustosmiranda@hotmail.com
License: UNKNOWN
Platform: UNKNOWN
Classifier: Programming Language :: Python :: 3
Classifier: License :: OSI Approved :: MIT License
Classifier: Operating System :: OS Independent
